bashutils/__init__.py
bashutils/bashutils.py
bashutils/logmsg.py
bashutils/time.py
python_bash_utils-0.4.0.dist-info/LICENSE
python_bash_utils-0.4.0.dist-info/METADATA
python_bash_utils-0.4.0.dist-info/WHEEL
python_bash_utils-0.4.0.dist-info/top_level.txt
python_bash_utils-0.4.0.dist-info/RECORD
